src/__init__.py
src/comm/__init__.py
src/comm/comm.py
src/comm/docker_ver.py
src/core/__init__.py
src/core/core.py
src/core/init.py
src/dataset/__init__.py
src/dataset/loader.py
src/dataset/named_entity_recognition/spacy.py
src/dataset/object_detection/labelbox.py
src/dataset/object_detection/yolo.py
src/storage/__init__.py
src/storage/classes/__init__.py
src/storage/classes/gcs.py
src/storage/classes/local.py
src/storage/classes/s3.py
src/training/__init__.py
src/training/projects.py
src/user/__init__.py
src/user/database/__init__.py
src/user/database/database.py
src/user/license/__init__.py
src/user/license/license.py
src/user/user.py
stack_api/__init__.py
stack_api/api_cli.py
stack_api/api_core.py
stack_api/api_web.py
stack_api/example_filter.json
stackcli-0.1.22.dist-info/entry_points.txt
stackcli-0.1.22.dist-info/WHEEL
stackcli-0.1.22.dist-info/METADATA
stackcli-0.1.22.dist-info/RECORD
