Metadata-Version: 2.1
Name: stackcli
Version: 0.1.22
Summary: 
Author: Toni Rosinol
Author-email: arosinol@stack-ai.com
Requires-Python: >=3.7,<4.0
Classifier: Programming Language :: Python :: 3
Classifier: Programming Language :: Python :: 3.7
Classifier: Programming Language :: Python :: 3.8
Classifier: Programming Language :: Python :: 3.9
Classifier: Programming Language :: Python :: 3.10
Classifier: Programming Language :: Python :: 3.11
Requires-Dist: boto3 (>=1.24.60,<2.0.0)
Requires-Dist: csv-diff
Requires-Dist: fastapi (>=0.80.0)
Requires-Dist: google-cloud-datastore (>=2.8.1,<3.0.0)
Requires-Dist: google-cloud-storage (>=2.5.0,<3.0.0)
Requires-Dist: maskpass (>=0.3.6,<0.4.0)
Requires-Dist: opencv-python (>=4.6.0.66)
Requires-Dist: pandas
Requires-Dist: pymongo (>=4.2.0,<5.0.0)
Requires-Dist: python-dotenv (>=0.20.0,<0.21.0)
Requires-Dist: typer[all] (>=0.6.1,<0.7.0)
Requires-Dist: tzlocal
